chromatix/__init__.py
chromatix/_about.py
chromatix-0.0.1.dist-info/LICENSE
chromatix-0.0.1.dist-info/METADATA
chromatix-0.0.1.dist-info/WHEEL
chromatix-0.0.1.dist-info/top_level.txt
chromatix-0.0.1.dist-info/RECORD
